CRC/rtl_model/settings/crc_config_4.vh
// 自动生成的CRC配置文件
// 配置类型: reflect

`define CRC_WIDTH 'd32
`define CRC_POLY 'h1d95f0ba3
`define CRC_INIT 'hffffffff
`define CRC_REFIN 'd1
`define CRC_REFOUT 'd1
`define CRC_XOROUT 'h0

CRC/rtl_model/settings/crc_config_3.vh
// 自动生成的CRC配置文件
// 配置类型: mixed_two

`define CRC_WIDTH 'd8
`define CRC_POLY 'h17f
`define CRC_INIT 'hff
`define CRC_REFIN 'd0
`define CRC_REFOUT 'd1
`define CRC_XOROUT 'h0

CRC/rtl_model/settings/crc_config_2.vh
// 自动生成的CRC配置文件
// 配置类型: mixed_one

`define CRC_WIDTH 'd32
`define CRC_POLY 'h14d96321f
`define CRC_INIT 'hffffffff
`define CRC_REFIN 'd1
`define CRC_REFOUT 'd0
`define CRC_XOROUT 'h0

CRC/rtl_model/settings/crc_config_1.vh
// 自动生成的CRC配置文件
// 配置类型: standard

`define CRC_WIDTH 'd32
`define CRC_POLY 'h1e207f383
`define CRC_INIT 'hffffffff
`define CRC_REFIN 'd0
`define CRC_REFOUT 'd0
`define CRC_XOROUT 'h0

CRC/rtl_model/src/crc_process_byte.v
module crc_process_byte #(
    parameter bits     = 8,
    parameter poly     = 8'h33
)
(
    input  refin_in,
    input  [8-1:0] byte_in,
    input  [bits-1:0] crc_in,
    output  reg [bits-1:0] crc_out
);

reg [7:0] byte_reg;
reg [bits-1:0] crc_reg;

integer i;

always@(*)begin
    byte_reg = refin_in? reflect(byte_in): byte_in;
    crc_reg =crc_in^(byte_reg<<(bits-8));
    crc_out =0;
    for(i=0;i<8;i=i+1)begin
        if(crc_reg[bits-1])begin
            crc_reg=((crc_reg<<1)^poly)&((1<<bits)-1);
        end
        else begin
            crc_reg=(crc_reg<<1)&((1<<bits)-1);
        end
    end
    crc_out =crc_reg;
end


// 位翻转函数实现
    function [7:0] reflect;
        input [7:0] data;
        integer i;
        begin
            reflect = 0;
            for (i = 0; i < 8; i = i + 1)
                reflect = reflect|(data[i]<<(7-i));
        end
    endfunction

endmodule

CRC/rtl_model/src/crc.v
`include "crc_process_byte.v"
module crc #(
    parameter bits =8,
    parameter poly =8'h33,
    parameter init =8'hff,
    parameter [0:0]refin =1'b0,
    parameter [0:0]refout =1'b0,
    parameter xorout =8'h00
)(
    input clk,
    input rst_n,
    input data_valid,
    input start,
    input [7:0] data_in,
    output reg crc_ready,
    output reg [bits-1:0] crc_out
);

// 内部寄存器
reg  [bits-1:0] crc_reg;
wire [bits-1:0] crc_next;
reg data_processed;  // 添加标志，指示是否有数据被处理过

//实列化字节处理模块
crc_process_byte #(.bits(bits),.poly(poly)) uut (
    .crc_in(crc_reg),
    .byte_in(data_in),
    .refin_in(refin),
    .crc_out(crc_next)
);

// 位翻转函数实现
    function [bits-1:0] reflect;
        input [bits-1:0] data;
        integer i;
        begin
            reflect = 0;
            for (i = 0; i < bits; i = i + 1)
                reflect = reflect|(data[i]<<(bits-1-i));
        end
    endfunction

always @(posedge clk or negedge rst_n) begin
    if(!rst_n) begin
        crc_reg <= init;
        crc_ready <= 0;
        crc_out <= 0;
        data_processed <= 0;
    end else if(start) begin
        // 开始新的计算
        crc_reg <= init;
        crc_ready <= 0;
        data_processed <= 0;
    end else if(data_valid) begin
        // 处理数据
        crc_reg <= crc_next;
        crc_ready <= 0;  // 数据处理中，结果未就绪
        data_processed <= 1;  // 标记已处理数据
    end else if (data_processed && !data_valid && !crc_ready) begin
        // 数据处理完成：已经处理过数据，当前无更多数据，结果未就绪
        if(refout) begin
            crc_out <= (reflect(crc_reg) ^ xorout) & ((1<<bits)-1);
        end else begin
            crc_out <= (crc_reg ^ xorout) & ((1<<bits)-1);
        end
        crc_ready <= 1;  // 结果就绪
    end
end

endmodule

CRC/rtl_model/sim/crc_tb.v
`timescale 1ns/1ns

// CRC配置选择
`define Crc_Standard 1
// `define Crc_Mixed1 1
// `define Crc_Mixed2 1
// `define Crc_Reverse 1

// 根据选择包含对应配置文件
`ifdef Crc_Standard
  `include "../settings/crc_config_1.vh"
`elsif Crc_Mixed1
  `include "../settings/crc_config_2.vh"
`elsif Crc_Mixed2
  `include "../settings/crc_config_3.vh"
`elsif Crc_Reverse
  `include "../settings/crc_config_4.vh"
`endif

// 包含CRC核心模块
`include "../src/crc.v"

module crc_tb;
    // 信号声明
    reg clk;
    reg rst_n;
    reg data_valid;
    reg start;
    reg [7:0] data_in;
    wire crc_ready;
    wire [`CRC_WIDTH-1:0] crc_out;
    
    // 文件处理
    integer input_file; // 输入文件
    integer output_file; // 输出文件
    integer scan_result; // 扫描结果
    
    // 测试数据存储
    integer data_length; // 数据长度
    reg [7:0] test_data [0:1023]; // 支持最多1024字节的测试数据
    integer i; // 循环计数器
    integer j; // 数据读取循环计数器
    integer max_tests = 4; // 最大测试数量
    reg [8*100:1] input_filename; // 输入文件名
    reg [8*100:1] output_filename; // 输出文件名
    reg valid_test; // 测试有效标志
    
    // 直接实例化CRC模块，不再使用crc_top作为中间层
    crc #(
        .bits(`CRC_WIDTH),
        .poly(`CRC_POLY),
        .init(`CRC_INIT),
        .refin(`CRC_REFIN),
        .refout(`CRC_REFOUT),
        .xorout(`CRC_XOROUT)
    ) crc_inst (
        .clk(clk),
        .rst_n(rst_n),
        .data_valid(data_valid),
        .start(start),
        .data_in(data_in),
        .crc_ready(crc_ready),
        .crc_out(crc_out)
    );
    
    // 时钟生成
    initial begin
        clk = 0;
        forever #5 clk = ~clk; // 10ns周期时钟
    end
    
    // 波形文件设置
    initial begin
        $dumpfile("crc_test.vcd");
        $dumpvars(0, crc_tb);
    end
    
    // 测试过程
    initial begin
        // 确定当前使用的配置
        $display("========= CRC配置信息 =========");
        
        // 简化的配置显示
        `ifdef Crc_Standard
            $display("当前使用: 标准模式");
        `endif
        
        `ifdef Crc_Mixed1
            $display("当前使用: 混合模式一");
        `endif
        
        `ifdef Crc_Mixed2
            $display("当前使用: 混合模式二");
        `endif
        
        `ifdef Crc_Reverse
            $display("当前使用: 反转模式");
        `endif
        
        $display("CRC宽度: %0d", `CRC_WIDTH);
        $display("CRC多项式: 0x%h", `CRC_POLY);
        $display("初始值: 0x%h", `CRC_INIT);
        $display("输入反转: %0d", `CRC_REFIN);
        $display("输出反转: %0d", `CRC_REFOUT);
        $display("结果异或值: 0x%h", `CRC_XOROUT);
        $display("===============================");
        
        // 循环处理每个测试文件
        for (i = 1; i <= max_tests; i = i + 1) begin
            valid_test = 1; // 初始假设测试有效
            
            // 构建文件名
            `ifdef Crc_Standard
                $sformat(input_filename, "../../dataset/Test_Model/input/test_data_c1_t%0d_input.dat", i);
                $sformat(output_filename, "../../dataset/Test_Model/rtl_data/test_data_c1_t%0d_output.dat", i);
            `elsif Crc_Mixed1
                $sformat(input_filename, "../../dataset/Test_Model/input/test_data_c2_t%0d_input.dat", i);
                $sformat(output_filename, "../../dataset/Test_Model/rtl_data/test_data_c2_t%0d_output.dat", i);
            `elsif Crc_Mixed2
                $sformat(input_filename, "../../dataset/Test_Model/input/test_data_c3_t%0d_input.dat", i);
                $sformat(output_filename, "../../dataset/Test_Model/rtl_data/test_data_c3_t%0d_output.dat", i);
            `elsif Crc_Reverse
                $sformat(input_filename, "../../dataset/Test_Model/input/test_data_c4_t%0d_input.dat", i);
                $sformat(output_filename, "../../dataset/Test_Model/rtl_data/test_data_c4_t%0d_output.dat", i);
            `endif
            
            // 打开测试数据文件
            input_file = $fopen(input_filename, "r");
            if (input_file == 0) begin
                $display("注意: 文件 %s 不存在或无法打开，跳过", input_filename);
                valid_test = 0; // 标记测试无效
            end
            
            if (valid_test) begin
                $display("\n===== 处理测试 #%0d =====", i);
                $display("输入文件: %s", input_filename);
                
                // 读取数据长度
                scan_result = $fscanf(input_file, "%d", data_length);
                if (scan_result != 1) begin
                    $display("错误: 无法读取数据长度");
                    $fclose(input_file);
                    valid_test = 0; // 标记测试无效
                end
            end
            
            if (valid_test) begin
                // 读取数据字节
                j = 0;
                valid_test = 1; // 重置有效标志
                
                while (j < data_length && valid_test) begin
                    scan_result = $fscanf(input_file, "%h", test_data[j]);
                    if (scan_result != 1) begin
                        $display("错误: 无法读取字节 %d", j);
                        valid_test = 0; // 标记测试无效
                    end else begin
                        j = j + 1;
                    end
                end
                
                // 关闭输入文件
                $fclose(input_file);
            end
            
            if (valid_test) begin
                // 开始CRC计算
                $display("数据长度: %d 字节", data_length);
                
                // 初始化信号
                rst_n = 0;
                data_valid = 0;
                start = 0;
                data_in = 0;
                
                // 重置CRC模块
                #20;
                rst_n = 1;
                #20;
                
                // 开始新的CRC计算
                start = 1;
                #10;
                start = 0;
                
                // 发送测试数据
                for (j = 0; j < data_length; j = j + 1) begin
                    data_in = test_data[j];
                    data_valid = 1;
                    #10;
                end
                
                // 停止数据输入，等待结果
                data_valid = 0;
                
                // 等待CRC计算完成
                wait(crc_ready);
                #10;
                
                // 显示结果
                $display("CRC结果: 0x%h", crc_out);
                
                // 保存结果到输出文件
                output_file = $fopen(output_filename, "w");
                if (output_file == 0) begin
                    $display("错误: 无法打开输出文件 %s", output_filename);
                end else begin
                    // 以十六进制格式写入CRC结果
                    $fdisplay(output_file, "%h", crc_out);
                    // 关闭输出文件
                    $fclose(output_file);
                    $display("结果已保存到: %s", output_filename);
                end
            end
        end
        
        $display("\n测试完成");
        $finish;
    end
    
endmodule

CRC/rtl_model/sim/crc_test.vcd
$date
	Sat Apr 19 22:14:47 2025
$end
$version
	Icarus Verilog
$end
$timescale
	1ns
$end
$scope module crc_tb $end
$var wire 1 ! crc_ready $end
$var wire 32 " crc_out [31:0] $end
$var reg 1 # clk $end
$var reg 8 $ data_in [7:0] $end
$var reg 1 % data_valid $end
$var reg 800 & input_filename [800:1] $end
$var reg 800 ' output_filename [800:1] $end
$var reg 1 ( rst_n $end
$var reg 1 ) start $end
$var reg 1 * valid_test $end
$var integer 32 + data_length [31:0] $end
$var integer 32 , i [31:0] $end
$var integer 32 - input_file [31:0] $end
$var integer 32 . j [31:0] $end
$var integer 32 / max_tests [31:0] $end
$var integer 32 0 output_file [31:0] $end
$var integer 32 1 scan_result [31:0] $end
$scope module crc_inst $end
$var wire 1 # clk $end
$var wire 8 2 data_in [7:0] $end
$var wire 1 % data_valid $end
$var wire 1 ( rst_n $end
$var wire 1 ) start $end
$var wire 32 3 crc_next [31:0] $end
$var parameter 32 4 bits $end
$var parameter 32 5 init $end
$var parameter 34 6 poly $end
$var parameter 1 7 refin $end
$var parameter 1 8 refout $end
$var parameter 32 9 xorout $end
$var reg 32 : crc_out [31:0] $end
$var reg 1 ! crc_ready $end
$var reg 32 ; crc_reg [31:0] $end
$var reg 1 < data_processed $end
$scope function reflect $end
$var reg 32 = data [31:0] $end
$var integer 32 > i [31:0] $end
$upscope $end
$scope module uut $end
$var wire 8 ? byte_in [7:0] $end
$var wire 32 @ crc_in [31:0] $end
$var wire 1 A refin_in $end
$var parameter 32 B bits $end
$var parameter 34 C poly $end
$var reg 8 D byte_reg [7:0] $end
$var reg 32 E crc_out [31:0] $end
$var reg 32 F crc_reg [31:0] $end
$var integer 32 G i [31:0] $end
$scope function reflect $end
$var reg 8 H data [7:0] $end
$var integer 32 I i [31:0] $end
$upscope $end
$upscope $end
$upscope $end
$upscope $end
$enddefinitions $end
$comment Show the parameter values. $end
$dumpall
b111100010000001111111001110000011 C
b100000 B
b0 9
08
07
b111100010000001111111001110000011 6
b11111111111111111111111111111111 5
b100000 4
$end
#0
$dumpvars
bx I
bx H
b1000 G
b1110001111100101000100011011 F
b1110001111100101000100011011 E
b0 D
0A
b11111111111111111111111111111111 @
b0 ?
bx >
bx =
0<
b11111111111111111111111111111111 ;
b0 :
b1110001111100101000100011011 3
b0 2
b1 1
bx 0
b100 /
b10100 .
b10000000000000000000000000000011 -
b1 ,
b10100 +
1*
0)
0(
b1011100010111000101111001011100010111000101111011001000110000101110100011000010111001101100101011101000010111101010100011001010111001101110100010111110100110101101111011001000110010101101100001011110111001001110100011011000101111101100100011000010111010001100001001011110111010001100101011100110111010001011111011001000110000101110100011000010101111101100011001100010101111101110100001100010101111101101111011101010111010001110000011101010111010000101110011001000110000101110100 '
b10111000101110001011110010111000101110001011110110010001100001011101000110000101110011011001010111010000101111010101000110010101110011011101000101111101001101011011110110010001100101011011000010111101101001011011100111000001110101011101000010111101110100011001010111001101110100010111110110010001100001011101000110000101011111011000110011000101011111011101000011000101011111011010010110111001110000011101010111010000101110011001000110000101110100 &
0%
b0 $
0#
b0 "
0!
$end
#5
1#
#10
0#
#15
1#
#20
0#
1(
#25
1#
#30
0#
#35
1#
#40
0#
1)
#45
1#
#50
b1000 G
b11000000101010001100001111000010 3
b11000000101010001100001111000010 E
b11000000101010001100001111000010 F
b100111 D
0#
1%
b100111 $
b100111 2
b100111 ?
b0 .
0)
#55
b1000 G
b10011011001010110100110100100 3
b10011011001010110100110100100 E
b10011011001010110100110100100 F
1<
b11000000101010001100001111000010 ;
b11000000101010001100001111000010 @
1#
#60
b1000 G
b11100001010111010000011000111111 3
b11100001010111010000011000111111 E
b11100001010111010000011000111111 F
b101001 D
0#
b101001 $
b101001 2
b101001 ?
b1 .
#65
b1000 G
b10110000000101100101010001101001 3
b10110000000101100101010001101001 E
b10110000000101100101010001101001 F
b11100001010111010000011000111111 ;
b11100001010111010000011000111111 @
1#
#70
b1000 G
b10001100101011000110010011001 3
b10001100101011000110010011001 E
b10001100101011000110010011001 F
b1001111 D
0#
b1001111 $
b1001111 2
b1001111 ?
b10 .
#75
b1000 G
b111000111000010001100010011010 3
b111000111000010001100010011010 E
b111000111000010001100010011010 F
b10001100101011000110010011001 ;
b10001100101011000110010011001 @
1#
#80
b1000 G
b10000110110010010101111000001011 3
b10000110110010010101111000001011 E
b10000110110010010101111000001011 F
b1000101 D
0#
b1000101 $
b1000101 2
b1000101 ?
b11 .
#85
b1000 G
b1111000011000011101010101111011 3
b1111000011000011101010101111011 E
b1111000011000011101010101111011 F
b10000110110010010101111000001011 ;
b10000110110010010101111000001011 @
1#
#90
b1000 G
b101101001011101101010000110110 3
b101101001011101101010000110110 E
b101101001011101101010000110110 F
b10011011 D
0#
b10011011 $
b10011011 2
b10011011 ?
b100 .
#95
b1000 G
b101000001000001000000000100110 3
b101000001000001000000000100110 E
b101000001000001000000000100110 F
b101101001011101101010000110110 ;
b101101001011101101010000110110 @
1#
#100
b1000 G
b1111011000110001010110111011110 3
b1111011000110001010110111011110 E
b1111011000110001010110111011110 F
b1011001 D
0#
b1011001 $
b1011001 2
b1011001 ?
b101 .
#105
b1000 G
b1111000001011001001011001010000 3
b1111000001011001001011001010000 E
b1111000001011001001011001010000 F
b1111011000110001010110111011110 ;
b1111011000110001010110111011110 @
1#
#110
b1000 G
b10100000011100010010111010110111 3
b10100000011100010010111010110111 E
b10100000011100010010111010110111 F
b11000111 D
0#
b11000111 $
b11000111 2
b11000111 ?
b110 .
#115
b1000 G
b110010101010101001110001110011 3
b110010101010101001110001110011 E
b110010101010101001110001110011 F
b10100000011100010010111010110111 ;
b10100000011100010010111010110111 @
1#
#120
b1000 G
b10111010110110100100101110110 3
b10111010110110100100101110110 E
b10111010110110100100101110110 F
b110100 D
0#
b110100 $
b110100 2
b110100 ?
b111 .
#125
b1000 G
b11011001110011111100110111010011 3
b11011001110011111100110111010011 E
b11011001110011111100110111010011 F
b10111010110110100100101110110 ;
b10111010110110100100101110110 @
1#
#130
b1000 G
b101011111101111010001001001000 3
b101011111101111010001001001000 E
b101011111101111010001001001000 F
b111010 D
0#
b111010 $
b111010 2
b111010 ?
b1000 .
#135
b1000 G
b11000111111000101110110000101000 3
b11000111111000101110110000101000 E
b11000111111000101110110000101000 F
b101011111101111010001001001000 ;
b101011111101111010001001001000 @
1#
#140
b1000 G
b10010100010110010101101101000011 3
b10010100010110010101101101000011 E
b10010100010110010101101101000011 F
b1010010 D
0#
b1010010 $
b1010010 2
b1010010 ?
b1001 .
#145
b1000 G
b1000110011100110100011111110010 3
b1000110011100110100011111110010 E
b1000110011100110100011111110010 F
b10010100010110010101101101000011 ;
b10010100010110010101101101000011 @
1#
#150
b1000 G
b11111101110101011110110001010110 3
b11111101110101011110110001010110 E
b11111101110101011110110001010110 F
b10110101 D
0#
b10110101 $
b10110101 2
b10110101 ?
b1010 .
#155
b1000 G
b11000000110111101011110110111110 3
b11000000110111101011110110111110 E
b11000000110111101011110110111110 F
b11111101110101011110110001010110 ;
b11111101110101011110110001010110 @
1#
#160
b1000 G
b10111001100000110100011100111010 3
b10111001100000110100011100111010 E
b10111001100000110100011100111010 F
b11100111 D
0#
b11100111 $
b11100111 2
b11100111 ?
b1011 .
#165
b1000 G
b101110001010101011101110011010 3
b101110001010101011101110011010 E
b101110001010101011101110011010 F
b10111001100000110100011100111010 ;
b10111001100000110100011100111010 @
1#
#170
b1000 G
b10001010001001111000111001011111 3
b10001010001001111000111001011111 E
b10001010001001111000111001011111 F
b1101100 D
0#
b1101100 $
b1101100 2
b1101100 ?
b1100 .
#175
b1000 G
b1111110001011110000011100100111 3
b1111110001011110000011100100111 E
b1111110001011110000011100100111 F
b10001010001001111000111001011111 ;
b10001010001001111000111001011111 @
1#
#180
b1000 G
b1101000011001111011011110001010 3
b1101000011001111011011110001010 E
b1101000011001111011011110001010 F
b1111111 D
0#
b1111111 $
b1111111 2
b1111111 ?
b1101 .
#185
b1000 G
b111101111011110001001110100111 3
b111101111011110001001110100111 E
b111101111011110001001110100111 F
b1101000011001111011011110001010 ;
b1101000011001111011011110001010 @
1#
#190
b1000 G
b11100101101100101010101101000000 3
b11100101101100101010101101000000 E
b11100101101100101010101101000000 F
b11100001 D
0#
b11100001 $
b11100001 2
b11100001 ?
b1110 .
#195
b1000 G
b11111110101110110110100100001010 3
b11111110101110110110100100001010 E
b11111110101110110110100100001010 F
b11100101101100101010101101000000 ;
b11100101101100101010101101000000 @
1#
#200
b1000 G
b1000000100100110010111110011011 3
b1000000100100110010111110011011 E
b1000000100100110010111110011011 F
b11101011 D
0#
b11101011 $
b11101011 2
b11101011 ?
b1111 .
#205
b1000 G
b1110001101010111111001000010000 3
b1110001101010111111001000010000 E
b1110001101010111111001000010000 F
b1000000100100110010111110011011 ;
b1000000100100110010111110011011 @
1#
#210
b1000 G
b10010010100001110000101010011 3
b10010010100001110000101010011 E
b10010010100001110000101010011 F
b10010010 D
0#
b10010010 $
b10010010 2
b10010010 ?
b10000 .
#215
b1000 G
b10101000110000111101001111010111 3
b10101000110000111101001111010111 E
b10101000110000111101001111010111 F
b10010010100001110000101010011 ;
b10010010100001110000101010011 @
1#
#220
b1000 G
b11001000010000101001101110000111 3
b11001000010000101001101110000111 E
b11001000010000101001101110000111 F
b10110000 D
0#
b10110000 $
b10110000 2
b10110000 ?
b10001 .
#225
b1000 G
b11000011011001110110011111000000 3
b11000011011001110110011111000000 E
b11000011011001110110011111000000 F
b11001000010000101001101110000111 ;
b11001000010000101001101110000111 @
1#
#230
b1000 G
b10111100110011100010101101100010 3
b10111100110011100010101101100010 E
b10111100110011100010101101100010 F
b1010100 D
0#
b1010100 $
b1010100 2
b1010100 ?
b10010 .
#235
b1000 G
b1100101101100100101010110111100 3
b1100101101100100101010110111100 E
b1100101101100100101010110111100 F
b10111100110011100010101101100010 ;
b10111100110011100010101101100010 @
1#
#240
b1000 G
b101101100001000011101111111 3
b101101100001000011101111111 E
b101101100001000011101111111 F
b11011100 D
0#
b11011100 $
b11011100 2
b11011100 ?
b10011 .
#245
b1000 G
b1101101110101111011000001000001 3
b1101101110101111011000001000001 E
b1101101110101111011000001000001 F
b101101100001000011101111111 ;
b101101100001000011101111111 @
1#
#250
0#
0%
b10100 .
#255
1!
b101101100001000011101111111 "
b101101100001000011101111111 :
1#
#260
0#
#265
0<
b0 "
b0 :
0!
b11111111111111111111111111111111 ;
b11111111111111111111111111111111 @
b1000 G
b1110001111100101000100011011 3
b1110001111100101000100011011 E
b1110001111100101000100011011 F
b0 D
1#
b0 $
b0 2
b0 ?
0(
b10001 .
b10001 +
b1011100010111000101111001011100010111000101111011001000110000101110100011000010111001101100101011101000010111101010100011001010111001101110100010111110100110101101111011001000110010101101100001011110111001001110100011011000101111101100100011000010111010001100001001011110111010001100101011100110111010001011111011001000110000101110100011000010101111101100011001100010101111101110100001100100101111101101111011101010111010001110000011101010111010000101110011001000110000101110100 '
b10111000101110001011110010111000101110001011110110010001100001011101000110000101110011011001010111010000101111010101000110010101110011011101000101111101001101011011110110010001100101011011000010111101101001011011100111000001110101011101000010111101110100011001010111001101110100010111110110010001100001011101000110000101011111011000110011000101011111011101000011001001011111011010010110111001110000011101010111010000101110011001000110000101110100 &
b10 ,
b10000000000000000000000000000011 0
#270
0#
#275
1#
#280
0#
#285
1#
1(
#290
0#
#295
1#
#300
0#
#305
1#
1)
#310
0#
#315
1<
b110001111010101111011101001010 ;
b110001111010101111011101001010 @
b1000 G
b10100011111010100001010010101100 3
b10100011111010100001010010101100 E
b10100011111010100001010010101100 F
b1110010 D
1#
1%
b1110010 $
b1110010 2
b1110010 ?
b0 .
0)
#320
0#
#325
b101110111110001010110100000110 ;
b101110111110001010110100000110 @
b1000 G
b11111110110110100010101010110101 3
b11111110110110100010101010110101 E
b11111110110110100010101010110101 F
b110010 D
1#
b110010 $
b110010 2
b110010 ?
b1 .
#330
0#
#335
b10111110101001111100000001000110 ;
b10111110101001111100000001000110 @
b1000 G
b11001011101011110101011100111010 3
b11001011101011110101011100111010 E
b11001011101011110101011100111010 F
b10100100 D
1#
b10100100 $
b10100100 2
b10100100 ?
b10 .
#340
0#
#345
b11000001101101011011100001110110 ;
b11000001101101011011100001110110 @
b1000 G
b11011010001011101010011010111010 3
b11011010001011101010011010111010 E
b11011010001011101010011010111010 F
b101010 D
1#
b101010 $
b101010 2
b101010 ?
b11 .
#350
0#
#355
b1100111011111001011101100111000 ;
b1100111011111001011101100111000 @
b1000 G
b1111010110011000001010010110101 3
b1111010110011000001010010110101 E
b1111010110011000001010010110101 F
b1111011 D
1#
b1111011 $
b1111011 2
b1111011 ?
b100 .
#360
0#
#365
b1000011111011000000010011000010 ;
b1000011111011000000010011000010 @
b1000 G
b11011001110010101000101100011101 3
b11011001110010101000101100011101 E
b11011001110010101000101100011101 F
b10111111 D
1#
b10111111 $
b10111111 2
b10111111 ?
b101 .
#370
0#
#375
b1100101110011001111111010 ;
b1100101110011001111111010 @
b1000 G
b11010001101110101010011011010101 3
b11010001101110101010011011010101 E
b11010001101110101010011011010101 F
b100001 D
1#
b100001 $
b100001 2
b100001 ?
b110 .
#380
0#
#385
b1000 G
b1011011010110001110011100000011 3
b1011011010110001110011100000011 E
b1011011010110001110011100000011 F
b11010001101110101010011011010101 ;
b11010001101110101010011011010101 @
1#
b111 .
#390
0#
#395
b1000010000001111100111101000100 ;
b1000010000001111100111101000100 @
b1000 G
b10001000001000110111000111110 3
b10001000001000110111000111110 E
b10001000001000110111000111110 F
b11111011 D
1#
b11111011 $
b11111011 2
b11111011 ?
b1000 .
#400
0#
#405
b10000011101111010100100111110101 ;
b10000011101111010100100111110101 @
b1000 G
b10101110000011000011001000001011 3
b10101110000011000011001000001011 E
b10101110000011000011001000001011 F
b11010111 D
1#
b11010111 $
b11010111 2
b11010111 ?
b1001 .
#410
0#
#415
b10001110011100110000101000111011 ;
b10001110011100110000101000111011 @
b1000 G
b1110110000001110100110010100110 3
b1110110000001110100110010100110 E
b1110110000001110100110010100110 F
b11001001 D
1#
b11001001 $
b11001001 2
b11001001 ?
b1010 .
#420
0#
#425
b111111100110011000100010011001 ;
b111111100110011000100010011001 @
b1000 G
b1011011111100000101001010110011 3
b1011011111100000101001010110011 E
b1011011111100000101001010110011 F
b100000 D
1#
b100000 $
b100000 2
b100000 ?
b1011 .
#430
0#
#435
b101011010011101000011011111011 ;
b101011010011101000011011111011 @
b1000 G
b1100010000101111001101001011010 3
b1100010000101111001101001011010 E
b1100010000101111001101001011010 F
b1101 D
1#
b1101 $
b1101 2
b1101 ?
b1100 .
#440
0#
#445
b1110111001001010111000111100100 ;
b1110111001001010111000111100100 @
b1000 G
b10010111101101111111101111111011 3
b10010111101101111111101111111011 E
b10010111101101111111101111111011 F
b1000101 D
1#
b1000101 $
b1000101 2
b1000101 ?
b1101 .
#450
0#
#455
b11110001010000011001111100011110 ;
b11110001010000011001111100011110 @
b1000 G
b111100101011101100001000110 3
b111100101011101100001000110 E
b111100101011101100001000110 F
b1111011 D
1#
b1111011 $
b1111011 2
b1111011 ?
b1110 .
#460
0#
#465
b101110000010011100111010111010 ;
b101110000010011100111010111010 @
b1000 G
b11010001000100001001100001110100 3
b11010001000100001001100001110100 E
b11010001000100001001100001110100 F
b11010 D
1#
b11010 $
b11010 2
b11010 ?
b1111 .
#470
0#
#475
b1100000101011001101110010011100 ;
b1100000101011001101110010011100 @
b1000 G
b10111010100101000010110010101101 3
b10111010100101000010110010101101 E
b10111010100101000010110010101101 F
b1110011 D
1#
b1110011 $
b1110011 2
b1110011 ?
b10000 .
#480
0#
#485
1!
b1100000101011001101110010011100 "
b1100000101011001101110010011100 :
1#
0%
b10001 .
#490
0#
#495
0<
b0 "
b0 :
0!
b11111111111111111111111111111111 ;
b11111111111111111111111111111111 @
b1000 G
b1110001111100101000100011011 3
b1110001111100101000100011011 E
b1110001111100101000100011011 F
b0 D
1#
b0 $
b0 2
b0 ?
0(
b1101 .
b1101 +
b1011100010111000101111001011100010111000101111011001000110000101110100011000010111001101100101011101000010111101010100011001010111001101110100010111110100110101101111011001000110010101101100001011110111001001110100011011000101111101100100011000010111010001100001001011110111010001100101011100110111010001011111011001000110000101110100011000010101111101100011001100010101111101110100001100110101111101101111011101010111010001110000011101010111010000101110011001000110000101110100 '
b10111000101110001011110010111000101110001011110110010001100001011101000110000101110011011001010111010000101111010101000110010101110011011101000101111101001101011011110110010001100101011011000010111101101001011011100111000001110101011101000010111101110100011001010111001101110100010111110110010001100001011101000110000101011111011000110011000101011111011101000011001101011111011010010110111001110000011101010111010000101110011001000110000101110100 &
b11 ,
#500
0#
#505
1#
#510
0#
#515
1#
1(
#520
0#
#525
1#
#530
0#
#535
1#
1)
#540
0#
#545
1<
b1011101100001011110011001110000 ;
b1011101100001011110011001110000 @
b1000 G
b10111111001111111010000111110111 3
b10111111001111111010000111110111 E
b10111111001111111010000111110111 F
b1101000 D
1#
1%
b1101000 $
b1101000 2
b1101000 ?
b0 .
0)
#550
0#
#555
b11110000010101011101001111101110 ;
b11110000010101011101001111101110 @
b1000 G
b10101000111111000001100101110001 3
b10101000111111000001100101110001 E
b10101000111111000001100101110001 F
b110111 D
1#
b110111 $
b110111 2
b110111 ?
b1 .
#560
0#
#565
b1001010111110111110101011110010 ;
b1001010111110111110101011110010 @
b1000 G
b110110000001100011101111001010 3
b110110000001100011101111001010 E
b110110000001100011101111001010 F
b110110 D
1#
b110110 $
b110110 2
b110110 ?
b10 .
#570
0#
#575
b10000100110000000010010000110001 ;
b10000100110000000010010000110001 @
b1000 G
b111000000001101011000111010111 3
b111000000001101011000111010111 E
b111000000001101011000111010111 F
b100 D
1#
b100 $
b100 2
b100 ?
b11 .
#580
0#
#585
b10110110011011100101001101101110 ;
b10110110011011100101001101101110 @
b1000 G
b10101010110111110001001110010101 3
b10101010110111110001001110010101 E
b10101010110111110001001110010101 F
b11111 D
1#
b11111 $
b11111 2
b11111 ?
b100 .
#590
0#
#595
b111000111001011010111011001101 ;
b111000111001011010111011001101 @
b1000 G
b10111001000000101110001010000001 3
b10111001000000101110001010000001 E
b10111001000000101110001010000001 F
b10011001 D
1#
b10011001 $
b10011001 2
b10011001 ?
b101 .
#600
0#
#605
b10000101101011000001111111000011 ;
b10000101101011000001111111000011 @
b1000 G
b10010110110001100001001011110111 3
b10010110110001100001001011110111 E
b10010110110001100001001011110111 F
b10110000 D
1#
b10110000 $
b10110000 2
b10110000 ?
b110 .
#610
0#
#615
b10010011010010001111111111000010 ;
b10010011010010001111111111000010 @
b1000 G
b11001111111101111001010011100110 3
b11001111111101111001010011100110 E
b11001111111101111001010011100110 F
b1011101 D
1#
b1011101 $
b1011101 2
b1011101 ?
b111 .
#620
0#
#625
b10110000110111010100001011010111 ;
b10110000110111010100001011010111 @
b1000 G
b10100111111001101110110000000100 3
b10100111111001101110110000000100 E
b10100111111001101110110000000100 F
b10011 D
1#
b10011 $
b10011 2
b10011 ?
b1000 .
#630
0#
#635
b1010000110100111111010000111001 ;
b1010000110100111111010000111001 @
b1000 G
b1101101110111000111111110010001 3
b1101101110111000111111110010001 E
b1101101110111000111111110010001 F
b1011010 D
1#
b1011010 $
b1011010 2
b1011010 ?
b1001 .
#640
0#
#645
b1011000000100100011011010001100 ;
b1011000000100100011011010001100 @
b1000 G
b1111100001101000110011000 3
b1111100001101000110011000 E
b1111100001101000110011000 F
b10100110 D
1#
b10100110 $
b10100110 2
b10100110 ?
b1010 .
#650
0#
#655
b11110110110001101010101101010 ;
b11110110110001101010101101010 @
b1000 G
b110011001100011011011101001111 3
b110011001100011011011101001111 E
b110011001100011011011101001111 F
b1100000 D
1#
b1100000 $
b1100000 2
b1100000 ?
b1011 .
#660
0#
#665
b1110101101110001110101110011010 ;
b1110101101110001110101110011010 @
b1000 G
b10000010001100100100101111110111 3
b10000010001100100100101111110111 E
b10000010001100100100101111110111 F
b1000000 D
1#
b1000000 $
b1000000 2
b1000000 ?
b1100 .
#670
0#
#675
1!
b1110101101110001110101110011010 "
b1110101101110001110101110011010 :
1#
0%
b1101 .
#680
0#
